{
  "id": "bugio",
  "url": "https://sv1.bugio9.live",
  "name": "BugioTV",
  "color": "#e53935",
  "grid_number": 3,
  "image": {
    "type": "cover",
    "url": "https://sv1.bugio9.live/favicon.ico"
  },
  "groups": [
    {
      "id": "cate_football",
      "name": "⚽ Bóng Đá (4 LIVE)",
      "display": "vertical",
      "grid_number": 2,
      "enable_detail": false,
      "channels": [
        {
          "id": "bg-6dbbe6abe5",
          "name": "Đà Nẵng vs Thanh Hóa | 18:00 07/06",
          "type": "single",
          "display": "thumbnail-only",
          "enable_detail": false,
          "labels": [
            {
              "text": "● LIVE",
              "position": "top-left",
              "color": "#00000080",
              "text_color": "#ff4444"
            }
          ],
          "sources": [
            {
              "id": "src-6dbbe6abe5",
              "name": "BugioTV",
              "contents": [
                {
                  "id": "ct-6dbbe6abe5",
                  "name": "Đà Nẵng vs Thanh Hóa",
                  "streams": [
                    {
                      "id": "st-6dbbe6abe5",
                      "name": "BG",
                      "stream_links": [
                        {
                          "id": "lnk-41910bf543",
                          "name": "Link FHD",
                          "type": "hls",
                          "default": true,
                          "url": "https://bglive.yarncdn.live/live/bgtv_blv_khomuc/playlist.m3u8",
                          "request_headers": [
                            {
                              "key": "Referer",
                              "value": "https://sv1.bugio9.live/"
                            },
                            {
                              "key": "User-Agent",
                              "value": "Mozilla/5.0"
                            }
                          ]
                        }
                      ]
                    }
                  ]
                }
              ]
            }
          ],
          "org_metadata": {
            "league": "V.League 1",
            "team_a": "Đà Nẵng",
            "team_b": "Thanh Hóa",
            "logo_a": "https://upload.wikimedia.org/wikipedia/vi/thumb/f/fb/Logo_CLB_SHB_%C4%90%C3%A0_N%E1%BA%B5ng_3_sao.svg/500px-Logo_CLB_SHB_%C4%90%C3%A0_N%E1%BA%B5ng_3_sao.svg.png",
            "logo_b": "https://upload.wikimedia.org/wikipedia/vi/d/d2/Logo_CLB_%C4%90ATH.png",
            "start_time": "2026-06-07T18:00:00",
            "blv": "BLV khô Mực",
            "is_live": true,
            "cate_type": "football"
          },
          "image": {
            "padding": 1,
            "background_color": "#ffffff",
            "display": "contain",
            "url": "https://raw.githubusercontent.com/jasminliu98/bugio-stream/refs/heads/main/thumbs/bg-6dbbe6abe5_d5353dcb_20260607.png?v=d5353dcb",
            "width": 1600,
            "height": 1200
          }
        },
        {
          "id": "bg-e586a4f55f",
          "name": "Song Lam Nghe An vs PVF_CAND | 18:00 07/06",
          "type": "single",
          "display": "thumbnail-only",
          "enable_detail": false,
          "labels": [
            {
              "text": "● LIVE",
              "position": "top-left",
              "color": "#00000080",
              "text_color": "#ff4444"
            }
          ],
          "sources": [
            {
              "id": "src-e586a4f55f",
              "name": "BugioTV",
              "contents": [
                {
                  "id": "ct-e586a4f55f",
                  "name": "Song Lam Nghe An vs PVF_CAND",
                  "streams": [
                    {
                      "id": "st-e586a4f55f",
                      "name": "BG",
                      "stream_links": [
                        {
                          "id": "lnk-51a73d71ba",
                          "name": "Link FHD",
                          "type": "hls",
                          "default": true,
                          "url": "https://bglive.yarncdn.live/live/bgtv_blv_mason/playlist.m3u8",
                          "request_headers": [
                            {
                              "key": "Referer",
                              "value": "https://sv1.bugio9.live/"
                            },
                            {
                              "key": "User-Agent",
                              "value": "Mozilla/5.0"
                            }
                          ]
                        }
                      ]
                    }
                  ]
                }
              ]
            }
          ],
          "org_metadata": {
            "league": "V.League 1",
            "team_a": "Sông Lam Nghệ An",
            "team_b": "PVF_CAND",
            "logo_a": "https://www.slnafc.com/logo.png",
            "logo_b": "https://ssl.gstatic.com/onebox/media/sports/logos/optimized/RA-eCdPplqA3mC1RTUtWtg_96x96.png",
            "start_time": "2026-06-07T18:00:00",
            "blv": "BLV Mason",
            "is_live": true,
            "cate_type": "football"
          },
          "image": {
            "padding": 1,
            "background_color": "#ffffff",
            "display": "contain",
            "url": "https://raw.githubusercontent.com/jasminliu98/bugio-stream/refs/heads/main/thumbs/bg-e586a4f55f_b2ee2f1c_20260607.png?v=b2ee2f1c",
            "width": 1600,
            "height": 1200
          }
        },
        {
          "id": "bg-ccf8111910",
          "name": "Becamex TP.HCM vs Hoàng Anh Gia Lai | 18:00 07/06",
          "type": "single",
          "display": "thumbnail-only",
          "enable_detail": false,
          "labels": [
            {
              "text": "● LIVE",
              "position": "top-left",
              "color": "#00000080",
              "text_color": "#ff4444"
            }
          ],
          "sources": [
            {
              "id": "src-ccf8111910",
              "name": "BugioTV",
              "contents": [
                {
                  "id": "ct-ccf8111910",
                  "name": "Becamex TP.HCM vs Hoàng Anh Gia Lai",
                  "streams": [
                    {
                      "id": "st-ccf8111910",
                      "name": "BG",
                      "stream_links": [
                        {
                          "id": "lnk-378f040fcb",
                          "name": "Link FHD",
                          "type": "hls",
                          "default": true,
                          "url": "https://bglive.yarncdn.live/live/bgtv_blv_cuccu/playlist.m3u8",
                          "request_headers": [
                            {
                              "key": "Referer",
                              "value": "https://sv1.bugio9.live/"
                            },
                            {
                              "key": "User-Agent",
                              "value": "Mozilla/5.0"
                            }
                          ]
                        }
                      ]
                    }
                  ]
                }
              ]
            }
          ],
          "org_metadata": {
            "league": "V.League 1",
            "team_a": "Becamex TP.HCM",
            "team_b": "Hoàng Anh Gia Lai",
            "logo_a": "https://upload.wikimedia.org/wikipedia/vi/3/35/Logo_CLB_Becamex_TP.HCM.png",
            "logo_b": "https://upload.wikimedia.org/wikipedia/vi/0/0d/Ho%C3%A0ng_Anh_Gia_Lai_FC.png",
            "start_time": "2026-06-07T18:00:00",
            "blv": "BLV Cúc Cu",
            "is_live": true,
            "cate_type": "football"
          },
          "image": {
            "padding": 1,
            "background_color": "#ffffff",
            "display": "contain",
            "url": "https://raw.githubusercontent.com/jasminliu98/bugio-stream/refs/heads/main/thumbs/bg-ccf8111910_ec407454_20260607.png?v=ec407454",
            "width": 1600,
            "height": 1200
          }
        },
        {
          "id": "bg-2cbd9c5406",
          "name": "Viettel vs Công An Hà Nội | 18:00 07/06",
          "type": "single",
          "display": "thumbnail-only",
          "enable_detail": false,
          "labels": [
            {
              "text": "● LIVE",
              "position": "top-left",
              "color": "#00000080",
              "text_color": "#ff4444"
            }
          ],
          "sources": [
            {
              "id": "src-2cbd9c5406",
              "name": "BugioTV",
              "contents": [
                {
                  "id": "ct-2cbd9c5406",
                  "name": "Viettel vs Công An Hà Nội",
                  "streams": [
                    {
                      "id": "st-2cbd9c5406",
                      "name": "BG",
                      "stream_links": [
                        {
                          "id": "lnk-0ba3f9d037",
                          "name": "Link FHD",
                          "type": "hls",
                          "default": true,
                          "url": "https://bglive.yarncdn.live/live/bgtv_blv_trada/playlist.m3u8",
                          "request_headers": [
                            {
                              "key": "Referer",
                              "value": "https://sv1.bugio9.live/"
                            },
                            {
                              "key": "User-Agent",
                              "value": "Mozilla/5.0"
                            }
                          ]
                        }
                      ]
                    }
                  ]
                }
              ]
            }
          ],
          "org_metadata": {
            "league": "V.League 1",
            "team_a": "Viettel",
            "team_b": "Công An Hà Nội",
            "logo_a": "https://ssl.gstatic.com/onebox/media/sports/logos/optimized/fn-O2zrDPGnWVwdulFs7sg_96x96.png",
            "logo_b": "https://ssl.gstatic.com/onebox/media/sports/logos/optimized/QuErRQm0uonT9Q21rRFEQw_96x96.png",
            "start_time": "2026-06-07T18:00:00",
            "blv": "BLV Tiểu Trà Đá",
            "is_live": true,
            "cate_type": "football"
          },
          "image": {
            "padding": 1,
            "background_color": "#ffffff",
            "display": "contain",
            "url": "https://raw.githubusercontent.com/jasminliu98/bugio-stream/refs/heads/main/thumbs/bg-2cbd9c5406_6eb86a6d_20260607.png?v=6eb86a6d",
            "width": 1600,
            "height": 1200
          }
        },
        {
          "id": "bg-54fe976ba1",
          "name": "Indonesia U19 vs Vietnam U19 | 20:00 07/06",
          "type": "single",
          "display": "thumbnail-only",
          "enable_detail": false,
          "labels": [
            {
              "text": "🕐 Sắp",
              "position": "top-left",
              "color": "#00000080",
              "text_color": "#aaaaaa"
            }
          ],
          "sources": [
            {
              "id": "src-54fe976ba1",
              "name": "BugioTV",
              "contents": [
                {
                  "id": "ct-54fe976ba1",
                  "name": "Indonesia U19 vs Vietnam U19",
                  "streams": [
                    {
                      "id": "st-54fe976ba1",
                      "name": "BG",
                      "stream_links": [
                        {
                          "id": "lnk-0ba3f9d037",
                          "name": "Link FHD",
                          "type": "hls",
                          "default": true,
                          "url": "https://bglive.yarncdn.live/live/bgtv_blv_trada/playlist.m3u8",
                          "request_headers": [
                            {
                              "key": "Referer",
                              "value": "https://sv1.bugio9.live/"
                            },
                            {
                              "key": "User-Agent",
                              "value": "Mozilla/5.0"
                            }
                          ]
                        }
                      ]
                    }
                  ]
                }
              ]
            }
          ],
          "org_metadata": {
            "league": "ASEAN Championship U19",
            "team_a": "Indonesia U19",
            "team_b": "Vietnam U19",
            "logo_a": "https://media.api-sports.io/football/teams/19149.png",
            "logo_b": "https://media.api-sports.io/football/teams/19157.png",
            "start_time": "2026-06-07T20:00:00",
            "blv": "BLV Tiểu Trà Đá",
            "is_live": false,
            "cate_type": "football"
          },
          "image": {
            "padding": 1,
            "background_color": "#ffffff",
            "display": "contain",
            "url": "https://raw.githubusercontent.com/jasminliu98/bugio-stream/refs/heads/main/thumbs/bg-54fe976ba1_130d825e_20260607.png?v=130d825e",
            "width": 1600,
            "height": 1200
          }
        },
        {
          "id": "bg-a35fe7f7fe",
          "name": "Indonesia U19 vs Vietnam U19 | 20:00 07/06",
          "type": "single",
          "display": "thumbnail-only",
          "enable_detail": false,
          "labels": [
            {
              "text": "🕐 Sắp",
              "position": "top-left",
              "color": "#00000080",
              "text_color": "#aaaaaa"
            }
          ],
          "sources": [
            {
              "id": "src-a35fe7f7fe",
              "name": "BugioTV",
              "contents": [
                {
                  "id": "ct-a35fe7f7fe",
                  "name": "Indonesia U19 vs Vietnam U19",
                  "streams": [
                    {
                      "id": "st-a35fe7f7fe",
                      "name": "BG",
                      "stream_links": [
                        {
                          "id": "lnk-378f040fcb",
                          "name": "Link FHD",
                          "type": "hls",
                          "default": true,
                          "url": "https://bglive.yarncdn.live/live/bgtv_blv_cuccu/playlist.m3u8",
                          "request_headers": [
                            {
                              "key": "Referer",
                              "value": "https://sv1.bugio9.live/"
                            },
                            {
                              "key": "User-Agent",
                              "value": "Mozilla/5.0"
                            }
                          ]
                        }
                      ]
                    }
                  ]
                }
              ]
            }
          ],
          "org_metadata": {
            "league": "ASEAN Championship U19",
            "team_a": "Indonesia U19",
            "team_b": "Vietnam U19",
            "logo_a": "https://media.api-sports.io/football/teams/19149.png",
            "logo_b": "https://media.api-sports.io/football/teams/19157.png",
            "start_time": "2026-06-07T20:00:00",
            "blv": "BLV Cúc Cu",
            "is_live": false,
            "cate_type": "football"
          },
          "image": {
            "padding": 1,
            "background_color": "#ffffff",
            "display": "contain",
            "url": "https://raw.githubusercontent.com/jasminliu98/bugio-stream/refs/heads/main/thumbs/bg-a35fe7f7fe_130d825e_20260607.png?v=130d825e",
            "width": 1600,
            "height": 1200
          }
        },
        {
          "id": "bg-03b264c595",
          "name": "Timor-Leste U19 vs Myanmar U19 | 20:00 07/06",
          "type": "single",
          "display": "thumbnail-only",
          "enable_detail": false,
          "labels": [
            {
              "text": "🕐 Sắp",
              "position": "top-left",
              "color": "#00000080",
              "text_color": "#aaaaaa"
            }
          ],
          "sources": [
            {
              "id": "src-03b264c595",
              "name": "BugioTV",
              "contents": [
                {
                  "id": "ct-03b264c595",
                  "name": "Timor-Leste U19 vs Myanmar U19",
                  "streams": [
                    {
                      "id": "st-03b264c595",
                      "name": "BG",
                      "stream_links": [
                        {
                          "id": "lnk-02ff9c6e74",
                          "name": "Link FHD",
                          "type": "hls",
                          "default": true,
                          "url": "https://bglive.yarncdn.live/live/bgtv_blv_tieuhac/playlist.m3u8",
                          "request_headers": [
                            {
                              "key": "Referer",
                              "value": "https://sv1.bugio9.live/"
                            },
                            {
                              "key": "User-Agent",
                              "value": "Mozilla/5.0"
                            }
                          ]
                        }
                      ]
                    }
                  ]
                }
              ]
            }
          ],
          "org_metadata": {
            "league": "ASEAN Championship U19",
            "team_a": "Timor-Leste U19",
            "team_b": "Myanmar U19",
            "logo_a": "https://upload.wikimedia.org/wikipedia/commons/thumb/2/26/Flag_of_East_Timor.svg/960px-Flag_of_East_Timor.svg.png",
            "logo_b": "https://media.api-sports.io/football/teams/19152.png",
            "start_time": "2026-06-07T20:00:00",
            "blv": "BLV Tiểu Hạc",
            "is_live": false,
            "cate_type": "football"
          },
          "image": {
            "padding": 1,
            "background_color": "#ffffff",
            "display": "contain",
            "url": "https://raw.githubusercontent.com/jasminliu98/bugio-stream/refs/heads/main/thumbs/bg-03b264c595_8154656e_20260607.png?v=8154656e",
            "width": 1600,
            "height": 1200
          }
        },
        {
          "id": "bg-415585bd38",
          "name": "Estonia U21 vs Lithuania U21 | 22:00 07/06",
          "type": "single",
          "display": "thumbnail-only",
          "enable_detail": false,
          "labels": [
            {
              "text": "🕐 Sắp",
              "position": "top-left",
              "color": "#00000080",
              "text_color": "#aaaaaa"
            }
          ],
          "sources": [
            {
              "id": "src-415585bd38",
              "name": "BugioTV",
              "contents": [
                {
                  "id": "ct-415585bd38",
                  "name": "Estonia U21 vs Lithuania U21",
                  "streams": [
                    {
                      "id": "st-415585bd38",
                      "name": "BG",
                      "stream_links": [
                        {
                          "id": "lnk-41910bf543",
                          "name": "Link FHD",
                          "type": "hls",
                          "default": true,
                          "url": "https://bglive.yarncdn.live/live/bgtv_blv_khomuc/playlist.m3u8",
                          "request_headers": [
                            {
                              "key": "Referer",
                              "value": "https://sv1.bugio9.live/"
                            },
                            {
                              "key": "User-Agent",
                              "value": "Mozilla/5.0"
                            }
                          ]
                        }
                      ]
                    }
                  ]
                }
              ]
            }
          ],
          "org_metadata": {
            "league": "INT FRL",
            "team_a": "Estonia U21 ",
            "team_b": "Lithuania U21",
            "logo_a": "https://img0.aiscore.com/football/team/a770d5b9d11809e44a587ffccf775248.png!w60",
            "logo_b": "https://img0.aiscore.com/football/team/f2b6806d6ed60d2d87b0dd5ae62e6f20.png!w60",
            "start_time": "2026-06-07T22:00:00",
            "blv": "BLV khô Mực",
            "is_live": false,
            "cate_type": "football"
          },
          "image": {
            "padding": 1,
            "background_color": "#ffffff",
            "display": "contain",
            "url": "https://raw.githubusercontent.com/jasminliu98/bugio-stream/refs/heads/main/thumbs/bg-415585bd38_6acb3a57_20260607.png?v=6acb3a57",
            "width": 1600,
            "height": 1200
          }
        },
        {
          "id": "bg-240ac9371e",
          "name": "Đan Mạch vs Ukraine | 23:30 07/06",
          "type": "single",
          "display": "thumbnail-only",
          "enable_detail": false,
          "labels": [
            {
              "text": "🕐 Sắp",
              "position": "top-left",
              "color": "#00000080",
              "text_color": "#aaaaaa"
            }
          ],
          "sources": [
            {
              "id": "src-240ac9371e",
              "name": "BugioTV",
              "contents": [
                {
                  "id": "ct-240ac9371e",
                  "name": "Đan Mạch vs Ukraine",
                  "streams": [
                    {
                      "id": "st-240ac9371e",
                      "name": "BG",
                      "stream_links": [
                        {
                          "id": "lnk-a4a6a520ed",
                          "name": "Link FHD",
                          "type": "hls",
                          "default": true,
                          "url": "https://bglive.yarncdn.live/live/bgtv_blv_lavie/playlist.m3u8",
                          "request_headers": [
                            {
                              "key": "Referer",
                              "value": "https://sv1.bugio9.live/"
                            },
                            {
                              "key": "User-Agent",
                              "value": "Mozilla/5.0"
                            }
                          ]
                        }
                      ]
                    }
                  ]
                }
              ]
            }
          ],
          "org_metadata": {
            "league": "Friendlies",
            "team_a": "Đan Mạch",
            "team_b": "Ukraine",
            "logo_a": "https://media.api-sports.io/football/teams/21.png",
            "logo_b": "https://media.api-sports.io/football/teams/772.png",
            "start_time": "2026-06-07T23:30:00",
            "blv": "BLV Lavie",
            "is_live": false,
            "cate_type": "football"
          },
          "image": {
            "padding": 1,
            "background_color": "#ffffff",
            "display": "contain",
            "url": "https://raw.githubusercontent.com/jasminliu98/bugio-stream/refs/heads/main/thumbs/bg-240ac9371e_c163b8e7_20260607.png?v=c163b8e7",
            "width": 1600,
            "height": 1200
          }
        }
      ]
    }
  ]
}