{
  "id": "bugio",
  "url": "https://sv1.bugio9.live",
  "name": "BugioTV",
  "color": "#e53935",
  "grid_number": 3,
  "image": {
    "type": "cover",
    "url": "https://sv1.bugio9.live/favicon.ico"
  },
  "groups": [
    {
      "id": "cate_football",
      "name": "⚽ Bóng Đá (2 LIVE)",
      "display": "vertical",
      "grid_number": 2,
      "enable_detail": false,
      "channels": [
        {
          "id": "bg-358f9e7be0",
          "name": "Nữ Đài Loan ( Trung Quốc ) vs Nữ Hàn Quốc | 18:00 14/06",
          "type": "single",
          "display": "thumbnail-only",
          "enable_detail": false,
          "labels": [
            {
              "text": "● LIVE",
              "position": "top-left",
              "color": "#00000080",
              "text_color": "#ff4444"
            }
          ],
          "sources": [
            {
              "id": "src-358f9e7be0",
              "name": "BugioTV",
              "contents": [
                {
                  "id": "ct-358f9e7be0",
                  "name": "Nữ Đài Loan ( Trung Quốc ) vs Nữ Hàn Quốc",
                  "streams": [
                    {
                      "id": "st-358f9e7be0",
                      "name": "BG",
                      "stream_links": [
                        {
                          "id": "lnk-970b2a547c",
                          "name": "Link FHD",
                          "type": "hls",
                          "default": true,
                          "url": "https://bglive.yarncdn.live/live/bgtv_blv_phaothan/playlist.m3u8",
                          "request_headers": [
                            {
                              "key": "Referer",
                              "value": "https://sv1.bugio9.live/"
                            },
                            {
                              "key": "User-Agent",
                              "value": "Mozilla/5.0"
                            }
                          ]
                        }
                      ]
                    }
                  ]
                }
              ]
            }
          ],
          "org_metadata": {
            "league": "AVC Nations Cup 2026 ",
            "team_a": "Nữ Đài Loan ( Trung Quốc )",
            "team_b": "Nữ Hàn Quốc",
            "logo_a": "https://img0.aiscore.com/basketball/team/58daf23f06bd54cb577a106fba19b140.png!w60",
            "logo_b": "https://img0.aiscore.com/basketball/team/28f5dbb01c5311a46f8b163f972d66cb.png!w60",
            "start_time": "2026-06-14T18:00:00",
            "blv": "BLV Pháo",
            "is_live": true,
            "cate_type": "football"
          },
          "image": {
            "padding": 1,
            "background_color": "#ffffff",
            "display": "contain",
            "url": "https://raw.githubusercontent.com/jasminliu98/bugio-stream/refs/heads/main/thumbs/bg-358f9e7be0_30c53834_20260614.png?v=30c53834",
            "width": 1600,
            "height": 1200
          }
        },
        {
          "id": "bg-71e63ef5b7",
          "name": "Ulytau vs Zhenys | 19:00 14/06",
          "type": "single",
          "display": "thumbnail-only",
          "enable_detail": false,
          "labels": [
            {
              "text": "● LIVE",
              "position": "top-left",
              "color": "#00000080",
              "text_color": "#ff4444"
            }
          ],
          "sources": [
            {
              "id": "src-71e63ef5b7",
              "name": "BugioTV",
              "contents": [
                {
                  "id": "ct-71e63ef5b7",
                  "name": "Ulytau vs Zhenys",
                  "streams": [
                    {
                      "id": "st-71e63ef5b7",
                      "name": "BG",
                      "stream_links": [
                        {
                          "id": "lnk-51a73d71ba",
                          "name": "Link FHD",
                          "type": "hls",
                          "default": true,
                          "url": "https://bglive.yarncdn.live/live/bgtv_blv_mason/playlist.m3u8",
                          "request_headers": [
                            {
                              "key": "Referer",
                              "value": "https://sv1.bugio9.live/"
                            },
                            {
                              "key": "User-Agent",
                              "value": "Mozilla/5.0"
                            }
                          ]
                        }
                      ]
                    }
                  ]
                }
              ]
            }
          ],
          "org_metadata": {
            "league": "Premier League",
            "team_a": "Ulytau",
            "team_b": "Zhenys",
            "logo_a": "https://media.api-sports.io/football/teams/21010.png",
            "logo_b": "https://media.api-sports.io/football/teams/16611.png",
            "start_time": "2026-06-14T19:00:00",
            "blv": "BLV Mao Từn",
            "is_live": true,
            "cate_type": "football"
          },
          "image": {
            "padding": 1,
            "background_color": "#ffffff",
            "display": "contain",
            "url": "https://raw.githubusercontent.com/jasminliu98/bugio-stream/refs/heads/main/thumbs/bg-71e63ef5b7_e2eb4880_20260614.png?v=e2eb4880",
            "width": 1600,
            "height": 1200
          }
        },
        {
          "id": "bg-04fcc65450",
          "name": "Al Taliya vs Al Wahda | 20:00 14/06",
          "type": "single",
          "display": "thumbnail-only",
          "enable_detail": false,
          "labels": [
            {
              "text": "🕐 Sắp",
              "position": "top-left",
              "color": "#00000080",
              "text_color": "#aaaaaa"
            }
          ],
          "sources": [
            {
              "id": "src-04fcc65450",
              "name": "BugioTV",
              "contents": [
                {
                  "id": "ct-04fcc65450",
                  "name": "Al Taliya vs Al Wahda",
                  "streams": [
                    {
                      "id": "st-04fcc65450",
                      "name": "BG",
                      "stream_links": [
                        {
                          "id": "lnk-a4a6a520ed",
                          "name": "Link FHD",
                          "type": "hls",
                          "default": true,
                          "url": "https://bglive.yarncdn.live/live/bgtv_blv_lavie/playlist.m3u8",
                          "request_headers": [
                            {
                              "key": "Referer",
                              "value": "https://sv1.bugio9.live/"
                            },
                            {
                              "key": "User-Agent",
                              "value": "Mozilla/5.0"
                            }
                          ]
                        }
                      ]
                    }
                  ]
                }
              ]
            }
          ],
          "org_metadata": {
            "league": "Premier League",
            "team_a": "Al Taliya",
            "team_b": "Al Wahda",
            "logo_a": "https://media.api-sports.io/football/teams/9113.png",
            "logo_b": "https://media.api-sports.io/football/teams/8035.png",
            "start_time": "2026-06-14T20:00:00",
            "blv": "BLV Lavie",
            "is_live": false,
            "cate_type": "football"
          },
          "image": {
            "padding": 1,
            "background_color": "#ffffff",
            "display": "contain",
            "url": "https://raw.githubusercontent.com/jasminliu98/bugio-stream/refs/heads/main/thumbs/bg-04fcc65450_c33a0e52_20260614.png?v=c33a0e52",
            "width": 1600,
            "height": 1200
          }
        },
        {
          "id": "bg-12b668a1ad",
          "name": "Aktobe vs Altay | 22:00 14/06",
          "type": "single",
          "display": "thumbnail-only",
          "enable_detail": false,
          "labels": [
            {
              "text": "🕐 Sắp",
              "position": "top-left",
              "color": "#00000080",
              "text_color": "#aaaaaa"
            }
          ],
          "sources": [
            {
              "id": "src-12b668a1ad",
              "name": "BugioTV",
              "contents": [
                {
                  "id": "ct-12b668a1ad",
                  "name": "Aktobe vs Altay",
                  "streams": [
                    {
                      "id": "st-12b668a1ad",
                      "name": "BG",
                      "stream_links": [
                        {
                          "id": "lnk-a4a6a520ed",
                          "name": "Link FHD",
                          "type": "hls",
                          "default": true,
                          "url": "https://bglive.yarncdn.live/live/bgtv_blv_lavie/playlist.m3u8",
                          "request_headers": [
                            {
                              "key": "Referer",
                              "value": "https://sv1.bugio9.live/"
                            },
                            {
                              "key": "User-Agent",
                              "value": "Mozilla/5.0"
                            }
                          ]
                        }
                      ]
                    }
                  ]
                }
              ]
            }
          ],
          "org_metadata": {
            "league": "Premier League",
            "team_a": "Aktobe",
            "team_b": "Altay",
            "logo_a": "https://media.api-sports.io/football/teams/4563.png",
            "logo_b": "https://media.api-sports.io/football/teams/4544.png",
            "start_time": "2026-06-14T22:00:00",
            "blv": "BLV Lavie",
            "is_live": false,
            "cate_type": "football"
          },
          "image": {
            "padding": 1,
            "background_color": "#ffffff",
            "display": "contain",
            "url": "https://raw.githubusercontent.com/jasminliu98/bugio-stream/refs/heads/main/thumbs/bg-12b668a1ad_55709bb2_20260614.png?v=55709bb2",
            "width": 1600,
            "height": 1200
          }
        },
        {
          "id": "bg-90fd4f88f5",
          "name": "Đức vs Curaçao | 00:00 15/06",
          "type": "single",
          "display": "thumbnail-only",
          "enable_detail": false,
          "labels": [
            {
              "text": "🕐 Sắp",
              "position": "top-left",
              "color": "#00000080",
              "text_color": "#aaaaaa"
            }
          ],
          "sources": [
            {
              "id": "src-90fd4f88f5",
              "name": "BugioTV",
              "contents": [
                {
                  "id": "ct-90fd4f88f5",
                  "name": "Đức vs Curaçao",
                  "streams": [
                    {
                      "id": "st-90fd4f88f5",
                      "name": "BG",
                      "stream_links": [
                        {
                          "id": "lnk-51a73d71ba",
                          "name": "Link FHD",
                          "type": "hls",
                          "default": true,
                          "url": "https://bglive.yarncdn.live/live/bgtv_blv_mason/playlist.m3u8",
                          "request_headers": [
                            {
                              "key": "Referer",
                              "value": "https://sv1.bugio9.live/"
                            },
                            {
                              "key": "User-Agent",
                              "value": "Mozilla/5.0"
                            }
                          ]
                        }
                      ]
                    }
                  ]
                }
              ]
            }
          ],
          "org_metadata": {
            "league": "World Cup",
            "team_a": "Đức",
            "team_b": "Curaçao",
            "logo_a": "https://media.api-sports.io/football/teams/25.png",
            "logo_b": "https://media.api-sports.io/football/teams/5530.png",
            "start_time": "2026-06-15T00:00:00",
            "blv": "BLV Mao Từn",
            "is_live": false,
            "cate_type": "football"
          },
          "image": {
            "padding": 1,
            "background_color": "#ffffff",
            "display": "contain",
            "url": "https://raw.githubusercontent.com/jasminliu98/bugio-stream/refs/heads/main/thumbs/bg-90fd4f88f5_e0997fbb_20260614.png?v=e0997fbb",
            "width": 1600,
            "height": 1200
          }
        }
      ]
    },
    {
      "id": "cate_bongchuyen",
      "name": "🏐 Bóng Chuyền (1 LIVE)",
      "display": "vertical",
      "grid_number": 2,
      "enable_detail": false,
      "channels": [
        {
          "id": "bg-043c2ec6c6",
          "name": "Slovenia - Nhật Bản  | 19:00 14/06",
          "type": "single",
          "display": "thumbnail-only",
          "enable_detail": false,
          "labels": [
            {
              "text": "● LIVE",
              "position": "top-left",
              "color": "#00000080",
              "text_color": "#ff4444"
            }
          ],
          "sources": [
            {
              "id": "src-043c2ec6c6",
              "name": "BugioTV",
              "contents": [
                {
                  "id": "ct-043c2ec6c6",
                  "name": "Slovenia - Nhật Bản ",
                  "streams": [
                    {
                      "id": "st-043c2ec6c6",
                      "name": "BG",
                      "stream_links": [
                        {
                          "id": "lnk-378f040fcb",
                          "name": "Link FHD",
                          "type": "hls",
                          "default": true,
                          "url": "https://bglive.yarncdn.live/live/bgtv_blv_cuccu/playlist.m3u8",
                          "request_headers": [
                            {
                              "key": "Referer",
                              "value": "https://sv1.bugio9.live/"
                            },
                            {
                              "key": "User-Agent",
                              "value": "Mozilla/5.0"
                            }
                          ]
                        }
                      ]
                    }
                  ]
                }
              ]
            }
          ],
          "org_metadata": {
            "league": "Nations League Men's",
            "team_a": "Slovenia",
            "team_b": "Nhật Bản ",
            "logo_a": "https://static.flashscore.com/res/image/data/fBWBjchl-dWxvhZJm.png",
            "logo_b": "https://static.flashscore.com/res/image/data/f552VMEa-E1YhvyqD.png",
            "start_time": "2026-06-14T19:00:00",
            "blv": "BLV Cúc Cu",
            "is_live": true,
            "cate_type": "bongchuyen"
          },
          "image": {
            "padding": 1,
            "background_color": "#ffffff",
            "display": "contain",
            "url": "https://raw.githubusercontent.com/jasminliu98/bugio-stream/refs/heads/main/thumbs/bg-043c2ec6c6_00208878_20260614.png?v=00208878",
            "width": 1600,
            "height": 1200
          }
        },
        {
          "id": "bg-9f93557d30",
          "name": "Canada - Turkey | 01:30 15/06",
          "type": "single",
          "display": "thumbnail-only",
          "enable_detail": false,
          "labels": [
            {
              "text": "🕐 Sắp",
              "position": "top-left",
              "color": "#00000080",
              "text_color": "#aaaaaa"
            }
          ],
          "sources": [
            {
              "id": "src-9f93557d30",
              "name": "BugioTV",
              "contents": [
                {
                  "id": "ct-9f93557d30",
                  "name": "Canada - Turkey",
                  "streams": [
                    {
                      "id": "st-9f93557d30",
                      "name": "BG",
                      "stream_links": [
                        {
                          "id": "lnk-378f040fcb",
                          "name": "Link FHD",
                          "type": "hls",
                          "default": true,
                          "url": "https://bglive.yarncdn.live/live/bgtv_blv_cuccu/playlist.m3u8",
                          "request_headers": [
                            {
                              "key": "Referer",
                              "value": "https://sv1.bugio9.live/"
                            },
                            {
                              "key": "User-Agent",
                              "value": "Mozilla/5.0"
                            }
                          ]
                        }
                      ]
                    }
                  ]
                }
              ]
            }
          ],
          "org_metadata": {
            "league": "Nations League Men's",
            "team_a": "Canada ",
            "team_b": "Turkey",
            "logo_a": "https://static.flashscore.com/res/image/data/x8ugZxyS-QBQPB0xP.png",
            "logo_b": "https://static.flashscore.com/res/image/data/lAFdyowS-6ys9CWQj.png",
            "start_time": "2026-06-15T01:30:00",
            "blv": "BLV Cúc Cu",
            "is_live": false,
            "cate_type": "bongchuyen"
          },
          "image": {
            "padding": 1,
            "background_color": "#ffffff",
            "display": "contain",
            "url": "https://raw.githubusercontent.com/jasminliu98/bugio-stream/refs/heads/main/thumbs/bg-9f93557d30_063cd0c4_20260614.png?v=063cd0c4",
            "width": 1600,
            "height": 1200
          }
        },
        {
          "id": "bg-4eff072083",
          "name": "USA - Italy | 05:00 15/06",
          "type": "single",
          "display": "thumbnail-only",
          "enable_detail": false,
          "labels": [
            {
              "text": "🕐 Sắp",
              "position": "top-left",
              "color": "#00000080",
              "text_color": "#aaaaaa"
            }
          ],
          "sources": [
            {
              "id": "src-4eff072083",
              "name": "BugioTV",
              "contents": [
                {
                  "id": "ct-4eff072083",
                  "name": "USA - Italy",
                  "streams": [
                    {
                      "id": "st-4eff072083",
                      "name": "BG",
                      "stream_links": [
                        {
                          "id": "lnk-970b2a547c",
                          "name": "Link FHD",
                          "type": "hls",
                          "default": true,
                          "url": "https://bglive.yarncdn.live/live/bgtv_blv_phaothan/playlist.m3u8",
                          "request_headers": [
                            {
                              "key": "Referer",
                              "value": "https://sv1.bugio9.live/"
                            },
                            {
                              "key": "User-Agent",
                              "value": "Mozilla/5.0"
                            }
                          ]
                        }
                      ]
                    }
                  ]
                }
              ]
            }
          ],
          "org_metadata": {
            "league": "Nations League Men's",
            "team_a": "USA ",
            "team_b": "Italy",
            "logo_a": "https://static.flashscore.com/res/image/data/zoIpbvHG-W6UqXKEA.png",
            "logo_b": "https://static.flashscore.com/res/image/data/h6v1tOAr-xCsenx2O.png",
            "start_time": "2026-06-15T05:00:00",
            "blv": "BLV Pháo",
            "is_live": false,
            "cate_type": "bongchuyen"
          },
          "image": {
            "padding": 1,
            "background_color": "#ffffff",
            "display": "contain",
            "url": "https://raw.githubusercontent.com/jasminliu98/bugio-stream/refs/heads/main/thumbs/bg-4eff072083_324a6738_20260614.png?v=324a6738",
            "width": 1600,
            "height": 1200
          }
        }
      ]
    }
  ]
}