{
  "id": "bugio",
  "url": "https://sv1.bugio9.live",
  "name": "BugioTV",
  "color": "#e53935",
  "grid_number": 3,
  "image": {
    "type": "cover",
    "url": "https://sv1.bugio9.live/favicon.ico"
  },
  "groups": [
    {
      "id": "cate_football",
      "name": "⚽ Bóng Đá",
      "display": "vertical",
      "grid_number": 2,
      "enable_detail": false,
      "channels": [
        {
          "id": "bg-b28d8e3ccb",
          "name": "Leganes vs Huesca | 01:30 19/05",
          "type": "single",
          "display": "thumbnail-only",
          "enable_detail": false,
          "labels": [
            {
              "text": "🕐 Sắp",
              "position": "top-left",
              "color": "#00000080",
              "text_color": "#aaaaaa"
            }
          ],
          "sources": [
            {
              "id": "src-b28d8e3ccb",
              "name": "BugioTV",
              "contents": [
                {
                  "id": "ct-b28d8e3ccb",
                  "name": "Leganes vs Huesca",
                  "streams": [
                    {
                      "id": "st-b28d8e3ccb",
                      "name": "BG",
                      "stream_links": [
                        {
                          "id": "lnk-c23e936057",
                          "name": "Link FHD",
                          "type": "hls",
                          "default": true,
                          "url": "https://bglive.yarncdn.live/live/bgtv_blv_tieubaxa/playlist.m3u8",
                          "request_headers": [
                            {
                              "key": "Referer",
                              "value": "https://sv1.bugio9.live/"
                            },
                            {
                              "key": "User-Agent",
                              "value": "Mozilla/5.0"
                            }
                          ]
                        }
                      ]
                    }
                  ]
                }
              ]
            }
          ],
          "org_metadata": {
            "league": "Segunda División",
            "team_a": "Leganes",
            "team_b": "Huesca",
            "logo_a": "https://media.api-sports.io/football/teams/537.png",
            "logo_b": "https://media.api-sports.io/football/teams/726.png",
            "start_time": "2026-05-19T01:30:00",
            "blv": "BLV Tiểu Bà Xã",
            "is_live": false,
            "cate_type": "football"
          },
          "image": {
            "padding": 1,
            "background_color": "#ffffff",
            "display": "contain",
            "url": "https://raw.githubusercontent.com/jasminliu98/bugio-stream/refs/heads/main/thumbs/bg-b28d8e3ccb_953e4290_20260519.png?v=953e4290",
            "width": 1600,
            "height": 1200
          }
        },
        {
          "id": "bg-18a4e1366e",
          "name": "Arsenal vs Burnley | 02:00 19/05",
          "type": "single",
          "display": "thumbnail-only",
          "enable_detail": false,
          "labels": [
            {
              "text": "🕐 Sắp",
              "position": "top-left",
              "color": "#00000080",
              "text_color": "#aaaaaa"
            }
          ],
          "sources": [
            {
              "id": "src-18a4e1366e",
              "name": "BugioTV",
              "contents": [
                {
                  "id": "ct-18a4e1366e",
                  "name": "Arsenal vs Burnley",
                  "streams": [
                    {
                      "id": "st-18a4e1366e",
                      "name": "BG",
                      "stream_links": [
                        {
                          "id": "lnk-0ba3f9d037",
                          "name": "Link FHD",
                          "type": "hls",
                          "default": true,
                          "url": "https://bglive.yarncdn.live/live/bgtv_blv_trada/playlist.m3u8",
                          "request_headers": [
                            {
                              "key": "Referer",
                              "value": "https://sv1.bugio9.live/"
                            },
                            {
                              "key": "User-Agent",
                              "value": "Mozilla/5.0"
                            }
                          ]
                        }
                      ]
                    }
                  ]
                }
              ]
            }
          ],
          "org_metadata": {
            "league": "Premier League",
            "team_a": "Arsenal",
            "team_b": "Burnley",
            "logo_a": "https://media.api-sports.io/football/teams/42.png",
            "logo_b": "https://media.api-sports.io/football/teams/44.png",
            "start_time": "2026-05-19T02:00:00",
            "blv": "BLV Tiểu Trà Đá",
            "is_live": false,
            "cate_type": "football"
          },
          "image": {
            "padding": 1,
            "background_color": "#ffffff",
            "display": "contain",
            "url": "https://raw.githubusercontent.com/jasminliu98/bugio-stream/refs/heads/main/thumbs/bg-18a4e1366e_2f339d52_20260519.png?v=2f339d52",
            "width": 1600,
            "height": 1200
          }
        },
        {
          "id": "bg-adf7ee2dcf",
          "name": "Arsenal vs Burnley | 02:00 19/05",
          "type": "single",
          "display": "thumbnail-only",
          "enable_detail": false,
          "labels": [
            {
              "text": "🕐 Sắp",
              "position": "top-left",
              "color": "#00000080",
              "text_color": "#aaaaaa"
            }
          ],
          "sources": [
            {
              "id": "src-adf7ee2dcf",
              "name": "BugioTV",
              "contents": [
                {
                  "id": "ct-adf7ee2dcf",
                  "name": "Arsenal vs Burnley",
                  "streams": [
                    {
                      "id": "st-adf7ee2dcf",
                      "name": "BG",
                      "stream_links": [
                        {
                          "id": "lnk-02ff9c6e74",
                          "name": "Link FHD",
                          "type": "hls",
                          "default": true,
                          "url": "https://bglive.yarncdn.live/live/bgtv_blv_tieuhac/playlist.m3u8",
                          "request_headers": [
                            {
                              "key": "Referer",
                              "value": "https://sv1.bugio9.live/"
                            },
                            {
                              "key": "User-Agent",
                              "value": "Mozilla/5.0"
                            }
                          ]
                        }
                      ]
                    }
                  ]
                }
              ]
            }
          ],
          "org_metadata": {
            "league": "Premier League",
            "team_a": "Arsenal",
            "team_b": "Burnley",
            "logo_a": "https://media.api-sports.io/football/teams/42.png",
            "logo_b": "https://media.api-sports.io/football/teams/44.png",
            "start_time": "2026-05-19T02:00:00",
            "blv": "BLV Tiểu Hạc",
            "is_live": false,
            "cate_type": "football"
          },
          "image": {
            "padding": 1,
            "background_color": "#ffffff",
            "display": "contain",
            "url": "https://raw.githubusercontent.com/jasminliu98/bugio-stream/refs/heads/main/thumbs/bg-adf7ee2dcf_2f339d52_20260519.png?v=2f339d52",
            "width": 1600,
            "height": 1200
          }
        },
        {
          "id": "bg-1cc8a8ea51",
          "name": "Arsenal vs Burnley | 02:00 19/05",
          "type": "single",
          "display": "thumbnail-only",
          "enable_detail": false,
          "labels": [
            {
              "text": "🕐 Sắp",
              "position": "top-left",
              "color": "#00000080",
              "text_color": "#aaaaaa"
            }
          ],
          "sources": [
            {
              "id": "src-1cc8a8ea51",
              "name": "BugioTV",
              "contents": [
                {
                  "id": "ct-1cc8a8ea51",
                  "name": "Arsenal vs Burnley",
                  "streams": [
                    {
                      "id": "st-1cc8a8ea51",
                      "name": "BG",
                      "stream_links": [
                        {
                          "id": "lnk-448842e236",
                          "name": "Link FHD",
                          "type": "hls",
                          "default": true,
                          "url": "https://bglive.yarncdn.live/live/bgtv_blv_lenh/playlist.m3u8",
                          "request_headers": [
                            {
                              "key": "Referer",
                              "value": "https://sv1.bugio9.live/"
                            },
                            {
                              "key": "User-Agent",
                              "value": "Mozilla/5.0"
                            }
                          ]
                        }
                      ]
                    }
                  ]
                }
              ]
            }
          ],
          "org_metadata": {
            "league": "Premier League",
            "team_a": "Arsenal",
            "team_b": "Burnley",
            "logo_a": "https://media.api-sports.io/football/teams/42.png",
            "logo_b": "https://media.api-sports.io/football/teams/44.png",
            "start_time": "2026-05-19T02:00:00",
            "blv": "BLV Lềnh",
            "is_live": false,
            "cate_type": "football"
          },
          "image": {
            "padding": 1,
            "background_color": "#ffffff",
            "display": "contain",
            "url": "https://raw.githubusercontent.com/jasminliu98/bugio-stream/refs/heads/main/thumbs/bg-1cc8a8ea51_2f339d52_20260519.png?v=2f339d52",
            "width": 1600,
            "height": 1200
          }
        }
      ]
    }
  ]
}